Workbook

Sheet READ ME
B2: THE ARTIST BUDGET SPREADSHEET
B3: A free tool from THE ARTIST OPERATOR by Jamil Apostol · headline.world
B6: HOW TO USE THIS WORKBOOK
B7: 1. THE SPLIT — set your four-account percentages and your fixed monthly salary. Yellow cells (blue text) are yours to edit; everything else calculates.
B8: 2. YEAR MAP — pencil in expected income and costs per month. The sheet computes the split, flags FAT/LEAN months, and runs your war-chest balance.
B9: 3. SHOW TRACKER — one row per show: guarantee, door, merch, costs. Net settles automatically. The example row shows the format; overwrite it.
B10: 4. MERCH ITEMS — one row per item: run costs in, true unit cost, profit per unit, break-even units, and markup all calculate. Order nothing below a 3x markup without a reason.
B11: 5. DASHBOARD — the year in one screen: totals, salary coverage, runway in months. Nothing to edit here; it reads the other sheets.
B13: LEGEND
B14: Yellow cells with blue text = inputs you edit. Black text = formulas, leave them alone. The example rows contain realistic sample values — replace them with your own.
B16: THE RULES THIS SHEET ENFORCES (from 'The Artist's Money Year')
B17: • Every dollar that arrives gets split on arrival: Operating / Salary / Taxes / War Chest.
... B21: This is planning structure, not financial or tax advice — check the percentages against your own situation.

Sheet The Split
B2: THE SPLIT — set once a year, obey all year
B4: ACCOUNT | C4: % OF EVERY DOLLAR | E4: WHAT IT'S FOR
B5: Operating | C5: 0.5 | E5: Everything the operation spends: gear, gas, sessions, ads, software, strings.
B6: Salary | C6: 0.25 | E6: What you pay yourself — same amount, same day, every month.
B7: Taxes | C7: 0.15 | E7: Skimmed on arrival, untouchable. April thanks June.
B8: War Chest | C8: 0.1 | E8: Runway. What lets you say no to bad money.
B9: TOTAL (must equal 100%) | C9: =SUM(C5:C8) -> 1 | D9: =IF(ROUND(C9,4)=1,"OK","FIX") -> OK
B11: MY MONTHLY SALARY ($) | C11: 1500 | E11: The fixed number, however humble, that hits your personal account on the same day every month.
B12: RUNWAY TARGET (months) | C12: 4 | E12: Months of survival the war chest should hold by December.
B13: MONTHLY SURVIVAL COST ($) | C13: 2200 | E13: What one month of your life costs, personally — rent, food, phone. Used for the runway math.
B15: WAR CHEST BALANCE TODAY ($) | C15: 1000 | E15: Starting balance — the Year Map runs forward from this number.

Sheet Year Map
B2: THE YEAR MAP — expected money, month by month
B3: Yellow cells are estimates you edit. IN gets split by The Split; the war chest runs forward from its starting balance.
B5: MONTH | C5: SHOWS ($) | D5: MERCH ($) | E5: ROYALTIES ($) | F5: OTHER ($) | G5: TOTAL IN | H5: OPERATING COSTS ($) | I5: TO SALARY | J5: TO TAXES | K5: TO WAR CHEST | L5: NET MONTH | M5: WAR CHEST BAL | N5: FAT/LEAN
B6: Jan | C6: 400 | D6: 80 | E6: 120 | F6: 300 | G6: =SUM(C6:F6) -> 900 | H6: 350 | I6: ='The Split'!$C$6*G6 -> 225 | J6: ='The Split'!$C$7*G6 -> 135 | K6: ='The Split'!$C$8*G6 -> 90 | L6: =G6-H6-I6-J6-K6 -> 100 | M6: ='The Split'!$C$15+K6 -> 1090 | N6: =IF(G6>=1.25*AVERAGE($G$6:$G$17),"FAT",IF(G6<=0.75*AVERAGE($G$6:$G$17),"LEAN","—")) -> LEAN
B7: Feb | C7: 0 | D7: 0 | E7: 120 | F7: 300 | G7: =SUM(C7:F7) -> 420 | H7: 300 | I7: ='The Split'!$C$6*G7 -> 105 | J7: ='The Split'!$C$7*G7 -> 63 | K7: ='The Split'!$C$8*G7 -> 42 | L7: =G7-H7-I7-J7-K7 -> -90 | M7: =M6+K7 -> 1132 | N7: =IF(G7>=1.25*AVERAGE($G$6:$G$17),"FAT",IF(G7<=0.75*AVERAGE($G$6:$G$17),"LEAN","—")) -> LEAN
B8: Mar | C8: 1200 | D8: 300 | E8: 130 | F8: 300 | G8: =SUM(C8:F8) -> 1930 | H8: 700 | I8: ='The Split'!$C$6*G8 -> 482.5 | J8: ='The Split'!$C$7*G8 -> 289.5 | K8: ='The Split'!$C$8*G8 -> 193 | L8: =G8-H8-I8-J8-K8 -> 265 | M8: =M7+K8 -> 1325 | N8: =IF(G8>=1.25*AVERAGE($G$6:$G$17),"FAT",IF(G8<=0.75*AVERAGE($G$6:$G$17),"LEAN","—")) -> —
B9: Apr | C9: 800 | D9: 200 | E9: 125 | F9: 300 | G9: =SUM(C9:F9) -> 1425 | H9: 500 | I9: ='The Split'!$C$6*G9 -> 356.25 | J9: ='The Split'!$C$7*G9 -> 213.75 | K9: ='The Split'!$C$8*G9 -> 142.5 | L9: =G9-H9-I9-J9-K9 -> 212.5 | M9: =M8+K9 -> 1467.5 | N9: =IF(G9>=1.25*AVERAGE($G$6:$G$17),"FAT",IF(G9<=0.75*AVERAGE($G$6:$G$17),"LEAN","—")) -> LEAN
B10: May | C10: 1500 | D10: 450 | E10: 140 | F10: 0 | G10: =SUM(C10:F10) -> 2090 | H10: 800 | I10: ='The Split'!$C$6*G10 -> 522.5 | J10: ='The Split'!$C$7*G10 -> 313.5 | K10: ='The Split'!$C$8*G10 -> 209 | L10: =G10-H10-I10-J10-K10 -> 245 | M10: =M9+K10 -> 1676.5 | N10: =IF(G10>=1.25*AVERAGE($G$6:$G$17),"FAT",IF(G10<=0.75*AVERAGE($G$6:$G$17),"LEAN","—")) -> —
B11: Jun | C11: 2600 | D11: 900 | E11: 150 | F11: 0 | G11: =SUM(C11:F11) -> 3650 | H11: 1300 | I11: ='The Split'!$C$6*G11 -> 912.5 | J11: ='The Split'!$C$7*G11 -> 547.5 | K11: ='The Split'!$C$8*G11 -> 365 | L11: =G11-H11-I11-J11-K11 -> 525 | M11: =M10+K11 -> 2041.5 | N11: =IF(G11>=1.25*AVERAGE($G$6:$G$17),"FAT",IF(G11<=0.75*AVERAGE($G$6:$G$17),"LEAN","—")) -> FAT
B12: Jul | C12: 1800 | D12: 600 | E12: 160 | F12: 0 | G12: =SUM(C12:F12) -> 2560 | H12: 1000 | I12: ='The Split'!$C$6*G12 -> 640 | J12: ='The Split'!$C$7*G12 -> 384 | K12: ='The Split'!$C$8*G12 -> 256 | L12: =G12-H12-I12-J12-K12 -> 280 | M12: =M11+K12 -> 2297.5 | N12: =IF(G12>=1.25*AVERAGE($G$6:$G$17),"FAT",IF(G12<=0.75*AVERAGE($G$6:$G$17),"LEAN","—")) -> —
B13: Aug | C13: 3200 | D13: 1100 | E13: 170 | F13: 0 | G13: =SUM(C13:F13) -> 4470 | H13: 1500 | I13: ='The Split'!$C$6*G13 -> 1117.5 | J13: ='The Split'!$C$7*G13 -> 670.5 | K13: ='The Split'!$C$8*G13 -> 447 | L13: =G13-H13-I13-J13-K13 -> 735 | M13: =M12+K13 -> 2744.5 | N13: =IF(G13>=1.25*AVERAGE($G$6:$G$17),"FAT",IF(G13<=0.75*AVERAGE($G$6:$G$17),"LEAN","—")) -> FAT
B14: Sep | C14: 900 | D14: 250 | E14: 150 | F14: 300 | G14: =SUM(C14:F14) -> 1600 | H14: 500 | I14: ='The Split'!$C$6*G14 -> 400 | J14: ='The Split'!$C$7*G14 -> 240 | K14: ='The Split'!$C$8*G14 -> 160 | L14: =G14-H14-I14-J14-K14 -> 300 | M14: =M13+K14 -> 2904.5 | N14: =IF(G14>=1.25*AVERAGE($G$6:$G$17),"FAT",IF(G14<=0.75*AVERAGE($G$6:$G$17),"LEAN","—")) -> LEAN
B15: Oct | C15: 1400 | D15: 400 | E15: 155 | F15: 300 | G15: =SUM(C15:F15) -> 2255 | H15: 700 | I15: ='The Split'!$C$6*G15 -> 563.75 | J15: ='The Split'!$C$7*G15 -> 338.25 | K15: ='The Split'!$C$8*G15 -> 225.5 | L15: =G15-H15-I15-J15-K15 -> 427.5 | M15: =M14+K15 -> 3130 | N15: =IF(G15>=1.25*AVERAGE($G$6:$G$17),"FAT",IF(G15<=0.75*AVERAGE($G$6:$G$17),"LEAN","—")) -> —
B16: Nov | C16: 2000 | D16: 650 | E16: 160 | F16: 300 | G16: =SUM(C16:F16) -> 3110 | H16: 900 | I16: ='The Split'!$C$6*G16 -> 777.5 | J16: ='The Split'!$C$7*G16 -> 466.5 | K16: ='The Split'!$C$8*G16 -> 311 | L16: =G16-H16-I16-J16-K16 -> 655 | M16: =M15+K16 -> 3441 | N16: =IF(G16>=1.25*AVERAGE($G$6:$G$17),"FAT",IF(G16<=0.75*AVERAGE($G$6:$G$17),"LEAN","—")) -> FAT
B17: Dec | C17: 600 | D17: 150 | E17: 165 | F17: 300 | G17: =SUM(C17:F17) -> 1215 | H17: 400 | I17: ='The Split'!$C$6*G17 -> 303.75 | J17: ='The Split'!$C$7*G17 -> 182.25 | K17: ='The Split'!$C$8*G17 -> 121.5 | L17: =G17-H17-I17-J17-K17 -> 207.5 | M17: =M16+K17 -> 3562.5 | N17: =IF(G17>=1.25*AVERAGE($G$6:$G$17),"FAT",IF(G17<=0.75*AVERAGE($G$6:$G$17),"LEAN","—")) -> LEAN
B18: YEAR | C18: =SUM(C6:C17) -> 16400 | D18: =SUM(D6:D17) -> 5080 | E18: =SUM(E6:E17) -> 1745 | F18: =SUM(F6:F17) -> 2400 | G18: =SUM(G6:G17) -> 25625 | H18: =SUM(H6:H17) -> 8950 | I18: =SUM(I6:I17) -> 6406.25 | J18: =SUM(J6:J17) -> 3843.75 | ... L18: =SUM(L6:L17) -> 3862.5

Sheet Show Tracker
B2: THE SHOW TRACKER — settle every show the night it happens
B3: Row 6 is a worked example — overwrite it with your first show. NET = guarantee + door + merch − venue merch cut − costs.
B5: DATE | C5: CITY | D5: VENUE | E5: GUARANTEE ($) | F5: DOOR ($) | G5: MERCH GROSS ($) | H5: VENUE MERCH CUT % | I5: COSTS ($) | J5: MERCH CUT ($) | K5: NET ($)
B6: 2026-09-12 | C6: Reno, NV | D6: The Holland Project | E6: 250 | F6: 180 | G6: 320 | H6: 0.1 | I6: 120 | J6: =G6*H6 -> 32 | K6: =E6+F6+G6-J6-I6 -> 598
J7: =IF($C7="","",G7*H7) | K7: =IF($C7="","",E7+F7+G7-J7-I7)
J8: =IF($C8="","",G8*H8) | K8: =IF($C8="","",E8+F8+G8-J8-I8)
J9: =IF($C9="","",G9*H9) | K9: =IF($C9="","",E9+F9+G9-J9-I9)
J10: =IF($C10="","",G10*H10) | K10: =IF($C10="","",E10+F10+G10-J10-I10)
J11: =IF($C11="","",G11*H11) | K11: =IF($C11="","",E11+F11+G11-J11-I11)
J12: =IF($C12="","",G12*H12) | K12: =IF($C12="","",E12+F12+G12-J12-I12)
J13: =IF($C13="","",G13*H13) | K13: =IF($C13="","",E13+F13+G13-J13-I13)
J14: =IF($C14="","",G14*H14) | K14: =IF($C14="","",E14+F14+G14-J14-I14)
J15: =IF($C15="","",G15*H15) | K15: =IF($C15="","",E15+F15+G15-J15-I15)
J16: =IF($C16="","",G16*H16) | K16: =IF($C16="","",E16+F16+G16-J16-I16)
J17: =IF($C17="","",G17*H17) | K17: =IF($C17="","",E17+F17+G17-J17-I17)
J18: =IF($C18="","",G18*H18) | K18: =IF($C18="","",E18+F18+G18-J18-I18)
... J35: =IF($C35="","",G35*H35) | K35: =IF($C35="","",E35+F35+G35-J35-I35)
B37: TOTALS | E37: =SUM(E6:E35) -> 250 | F37: =SUM(F6:F35) -> 180 | G37: =SUM(G6:G35) -> 320 | I37: =SUM(I6:I35) -> 120 | J37: =SUM(J6:J35) -> 32 | K37: =SUM(K6:K35) -> 598

Sheet Merch Items
B2: MERCH ITEM CARDS — the math before the order
B3: Row 6 is a worked example. Break-even = total run cost ÷ profit per unit. Aim for markup ≥ 3.
B5: ITEM | C5: RUN SIZE | D5: RUN COST ($) | E5: SHIP/SETUP ($) | F5: TRUE UNIT COST | G5: PRICE ($) | H5: VENUE CUT % | I5: PROFIT / UNIT | J5: BREAK-EVEN UNITS | K5: MARKUP
B6: Tour tee (heavyweight) | C6: 72 | D6: 432 | E6: 55 | F6: =(D6+E6)/C6 -> 6.7638889 | G6: 25 | H6: 0.1 | I6: =G6*(1-H6)-F6 -> 15.736111 | J6: =IF(I6>0,ROUNDUP((D6+E6)/I6,0),"—") -> 31 | K6: =IF(F6>0,G6/F6,"—") -> 3.6960986
F7: =IF($C7="","",(D7+E7)/C7) | I7: =IF($C7="","",G7*(1-H7)-F7) | J7: =IF($C7="","",IF(I7>0,ROUNDUP((D7+E7)/I7,0),"—")) | K7: =IF($C7="","",IF(F7>0,G7/F7,"—"))
F8: =IF($C8="","",(D8+E8)/C8) | I8: =IF($C8="","",G8*(1-H8)-F8) | J8: =IF($C8="","",IF(I8>0,ROUNDUP((D8+E8)/I8,0),"—")) | K8: =IF($C8="","",IF(F8>0,G8/F8,"—"))
F9: =IF($C9="","",(D9+E9)/C9) | I9: =IF($C9="","",G9*(1-H9)-F9) | J9: =IF($C9="","",IF(I9>0,ROUNDUP((D9+E9)/I9,0),"—")) | K9: =IF($C9="","",IF(F9>0,G9/F9,"—"))
F10: =IF($C10="","",(D10+E10)/C10) | I10: =IF($C10="","",G10*(1-H10)-F10) | J10: =IF($C10="","",IF(I10>0,ROUNDUP((D10+E10)/I10,0),"—")) | K10: =IF($C10="","",IF(F10>0,G10/F10,"—"))
F11: =IF($C11="","",(D11+E11)/C11) | I11: =IF($C11="","",G11*(1-H11)-F11) | J11: =IF($C11="","",IF(I11>0,ROUNDUP((D11+E11)/I11,0),"—")) | K11: =IF($C11="","",IF(F11>0,G11/F11,"—"))
F12: =IF($C12="","",(D12+E12)/C12) | I12: =IF($C12="","",G12*(1-H12)-F12) | J12: =IF($C12="","",IF(I12>0,ROUNDUP((D12+E12)/I12,0),"—")) | K12: =IF($C12="","",IF(F12>0,G12/F12,"—"))
F13: =IF($C13="","",(D13+E13)/C13) | I13: =IF($C13="","",G13*(1-H13)-F13) | J13: =IF($C13="","",IF(I13>0,ROUNDUP((D13+E13)/I13,0),"—")) | K13: =IF($C13="","",IF(F13>0,G13/F13,"—"))
F14: =IF($C14="","",(D14+E14)/C14) | I14: =IF($C14="","",G14*(1-H14)-F14) | J14: =IF($C14="","",IF(I14>0,ROUNDUP((D14+E14)/I14,0),"—")) | K14: =IF($C14="","",IF(F14>0,G14/F14,"—"))
F15: =IF($C15="","",(D15+E15)/C15) | I15: =IF($C15="","",G15*(1-H15)-F15) | J15: =IF($C15="","",IF(I15>0,ROUNDUP((D15+E15)/I15,0),"—")) | K15: =IF($C15="","",IF(F15>0,G15/F15,"—"))
F16: =IF($C16="","",(D16+E16)/C16) | I16: =IF($C16="","",G16*(1-H16)-F16) | J16: =IF($C16="","",IF(I16>0,ROUNDUP((D16+E16)/I16,0),"—")) | K16: =IF($C16="","",IF(F16>0,G16/F16,"—"))
F17: =IF($C17="","",(D17+E17)/C17) | I17: =IF($C17="","",G17*(1-H17)-F17) | J17: =IF($C17="","",IF(I17>0,ROUNDUP((D17+E17)/I17,0),"—")) | K17: =IF($C17="","",IF(F17>0,G17/F17,"—"))
F18: =IF($C18="","",(D18+E18)/C18) | I18: =IF($C18="","",G18*(1-H18)-F18) | J18: =IF($C18="","",IF(I18>0,ROUNDUP((D18+E18)/I18,0),"—")) | K18: =IF($C18="","",IF(F18>0,G18/F18,"—"))

Sheet Dashboard
B2: THE YEAR IN ONE SCREEN
B3: Reads the other sheets. Nothing to edit here.
B5: Total in (Year Map) | C5: ='Year Map'!G18 -> 25625
B6: Operating costs (Year Map) | C6: ='Year Map'!H18 -> 8950
B7: Paid to salary | C7: ='Year Map'!I18 -> 6406.25
B8: Set aside for taxes | C8: ='Year Map'!J18 -> 3843.75
B9: Into the war chest | C9: ='Year Map'!K18 -> 2562.5
B10: War chest at year end | C10: ='Year Map'!M17 -> 3562.5
B11: Runway at year end (months) | C11: ='Year Map'!M17/'The Split'!C13 -> 1.6193182
B12: Runway target (months) | C12: ='The Split'!C12 -> 4
B13: Runway status | C13: =IF('Year Map'!M17/'The Split'!C13>='The Split'!C12,"ON TARGET","BEHIND") -> BEHIND
B14: Salary the split can fund monthly | C14: ='The Split'!C6*'Year Map'!G18/12 -> 533.85417
B15: Salary you set | C15: ='The Split'!C11 -> 1500
B16: Salary status | C16: =IF('The Split'!C6*'Year Map'!G18/12>='The Split'!C11,"COVERED","GAP — see Year Map") -> GAP — see Year Map
B17: Shows logged net (Show Tracker) | C17: ='Show Tracker'!K37 -> 598
